eikonax/__init__.py
eikonax/corefunctions.py
eikonax/derivator.py
eikonax/finitediff.py
eikonax/linalg.py
eikonax/logging.py
eikonax/preprocessing.py
eikonax/solver.py
eikonax/tensorfield.py
eikonax-0.4.2.dist-info/METADATA
eikonax-0.4.2.dist-info/WHEEL
eikonax-0.4.2.dist-info/licenses/LICENSE
eikonax-0.4.2.dist-info/RECORD
