Metadata-Version: 2.4
Name: eikonax
Version: 0.4.2
Summary: Differentiable Solver for the Anisotropic Eikonal Equation on Triangulated Meshes
Project-URL: repository, https://github.com/maximilian-kruse/Eikonax
Project-URL: documentation, https://maximilian-kruse.github.io/Eikonax/
Author-email: Maximilian Kruse <maxkruse1604@gmail.com>
Maintainer-email: Maximilian Kruse <maxkruse1604@gmail.com>
License: MIT
License-File: LICENSE
Keywords: GPU acceleration,automatic differentiation,eikonal equation
Classifier: Development Status :: 3 - Alpha
Classifier: Environment :: GPU :: NVIDIA CUDA
Classifier: Intended Audience :: Science/Research
Classifier: License :: OSI Approved :: MIT License
Classifier: Operating System :: POSIX :: Linux
Classifier: Programming Language :: Python :: 3
Requires-Python: ==3.13.*
Requires-Dist: beartype>=0.21
Requires-Dist: equinox>=0.13
Requires-Dist: jax>=0.7
Requires-Dist: jaxtyping>=0.3
Requires-Dist: numpy>=2.2
Requires-Dist: scipy>=1.16
